mastertickets/__init__.py
mastertickets/api.py
mastertickets/compat.py
mastertickets/db_default.py
mastertickets/graphviz.py
mastertickets/model.py
mastertickets/web_ui.py
mastertickets/htdocs/css/ticket.css
mastertickets/htdocs/img/caution.png
mastertickets/htdocs/img/checkmark.gif
mastertickets/htdocs/img/exclaim.png
mastertickets/htdocs/img/x.png
mastertickets/htdocs/js/disable_resolve.js
mastertickets/htdocs/js/linkify_blockedby.js
mastertickets/htdocs/js/linkify_blocking.js
mastertickets/templates/depgraph.html
mastertickets/upgrades/__init__.py
mastertickets/upgrades/db2.py
TracMasterTickets-4.0.4.dist-info/COPYING
TracMasterTickets-4.0.4.dist-info/METADATA
TracMasterTickets-4.0.4.dist-info/WHEEL
TracMasterTickets-4.0.4.dist-info/entry_points.txt
TracMasterTickets-4.0.4.dist-info/top_level.txt
TracMasterTickets-4.0.4.dist-info/RECORD
