Metadata-Version: 2.1
Name: TracMasterTickets
Version: 4.0.4
Summary: Provides ticket dependencies and master tickets.
Home-page: https://trac-hacks.org/wiki/MasterTicketsPlugin
Author: Noah Kantrowitz
Author-email: noah@coderanger.net
Maintainer: Ryan J Ollos
Maintainer-email: ryan.j.ollos@gmail.com
License: BSD 3-Clause
Keywords: trac plugin ticket dependencies master
Platform: UNKNOWN
Classifier: Framework :: Trac
Classifier: Development Status :: 5 - Production/Stable
Classifier: Environment :: Web Environment
Classifier: License :: OSI Approved :: BSD License
Classifier: Natural Language :: English
Classifier: Operating System :: OS Independent
Classifier: Programming Language :: Python
Requires-Dist: Trac
